README.md
setup.py
wtforms_field_factory.py
wtforms_field_factory.egg-info/PKG-INFO
wtforms_field_factory.egg-info/SOURCES.txt
wtforms_field_factory.egg-info/dependency_links.txt
wtforms_field_factory.egg-info/requires.txt
wtforms_field_factory.egg-info/top_level.txt