Metadata-Version: 2.1
Name: wtforms-field-factory
Version: 0.1
Summary: UNKNOWN
Home-page: https://github.com/v7a/wtforms-field-factory
Author: v7a
License: MIT
Project-URL: Source, https://github.com/v7a/wtforms-field-factory
Project-URL: Tracker, https://github.com/v7a/wtforms-field-factory/issues
Keywords: wtforms,field,factory,on-the-fly
Platform: UNKNOWN
Classifier: Development Status :: 3 - Alpha
Classifier: Intended Audience :: Developers
Classifier: Programming Language :: Python :: 3 :: Only
Classifier: License :: OSI Approved :: MIT License
Classifier: Operating System :: OS Independent
Classifier: Topic :: Internet :: WWW/HTTP
